edureception/__init__.py
edureception/actions.py
edureception/api.py
edureception/base.py
edureception/models.py
edureception/providers.py
edureception/ui.py
edureception/validators.py
edureception/migrations/0001_initial.py
edureception/migrations/__init__.py
edureception/report/__init__.py
edureception/report/actions.py
edureception/report/reporter.py
edureception/report/ui.py
edureception/scheduling/__init__.py
edureception/scheduling/actions.py
edureception/scheduling/ui.py
edureception/south_migrations/0001_initial.py
edureception/south_migrations/__init__.py
edureception/templates/report/schedule_print.xls
edureception/templates/ui-js/applicant-select-win.js
edureception/templates/ui-js/reception-cell-edit-window.js
edureception/templates/ui-js/reception-scheduling-edit.js
edureception/templates/ui-js/specialist-reception-grid.js
edureception/templates/ui-js/specialist-reception-report-win.js
edureception/templates/ui-js/specialist-reception-timetable-win.js
edureception/timetable/__init__.py
edureception/timetable/actions.py
edureception/timetable/ui.py
edureception/webservice/__init__.py
edureception/webservice/entities.py
edureception/webservice/errors.py
edureception/webservice/helpers.py
edureception/webservice/proxy.py
edureception/webservice/service.py
edureception-1.6.0.dist-info/METADATA
edureception-1.6.0.dist-info/WHEEL
edureception-1.6.0.dist-info/top_level.txt
edureception-1.6.0.dist-info/RECORD
