Metadata-Version: 2.4
Name: edureception
Version: 1.6.0
Summary: Пакет "Приема специалиста"
Home-page: https://stash.bars-open.ru/projects/EDUBASE/repos/specialist_reception
Author: BARS Group
Classifier: Intended Audience :: Developers
Classifier: Environment :: Web Environment
Classifier: Natural Language :: Russian
Classifier: Natural Language :: English
Classifier: Operating System :: OS Independent
Classifier: Development Status :: 5 - Production/Stable
Classifier: Programming Language :: Python
Classifier: Programming Language :: Python :: 3.6
Classifier: Framework :: Django :: 1.11
Classifier: Framework :: Django :: 4.0
Classifier: Framework :: Django :: 4.2
Requires-Dist: educommon
Requires-Dist: m3-django-compatibility<2.0,>=1.12.0
Requires-Dist: future
Dynamic: author
Dynamic: classifier
Dynamic: home-page
Dynamic: requires-dist
Dynamic: summary
